pytest_dolphin/__init__.py
pytest_dolphin/libfixtures.py
pytest_dolphin-0.3.9.dist-info/DESCRIPTION.rst
pytest_dolphin-0.3.9.dist-info/METADATA
pytest_dolphin-0.3.9.dist-info/RECORD
pytest_dolphin-0.3.9.dist-info/WHEEL
pytest_dolphin-0.3.9.dist-info/entry_points.txt
pytest_dolphin-0.3.9.dist-info/metadata.json
pytest_dolphin-0.3.9.dist-info/top_level.txt
