Metadata-Version: 2.0
Name: pytest-dolphin
Version: 0.3.9
Summary: Some extra stuff that we use ininternally
Home-page: https://github.com/dolphinkiss/pytest-dolphin
Author: Peter Lauri
Author-email: peterlauri@gmail.com
License: MIT
Platform: UNKNOWN
Classifier: Development Status :: 4 - Beta
Classifier: Framework :: Pytest
Classifier: Intended Audience :: Developers
Classifier: Topic :: Software Development :: Testing
Classifier: Programming Language :: Python
Classifier: Programming Language :: Python :: 2
Classifier: Programming Language :: Python :: 2.7
Classifier: Programming Language :: Python :: 3
Classifier: Programming Language :: Python :: 3.3
Classifier: Programming Language :: Python :: 3.4
Classifier: Programming Language :: Python :: 3.5
Classifier: Programming Language :: Python :: Implementation :: CPython
Classifier: Programming Language :: Python :: Implementation :: PyPy
Classifier: Operating System :: OS Independent
Classifier: License :: OSI Approved :: MIT License
Requires-Dist: django (<1.11)
Requires-Dist: pytest (==3.0.4)
Requires-Dist: pytest-cov (==2.4.0)
Requires-Dist: pytest-django (==3.1.2)
Requires-Dist: pytest-html (==1.12.0)
Requires-Dist: pytest-pythonpath (==0.7.1)
Requires-Dist: pytest-splinter (==1.7.7)
Requires-Dist: pytest-travis-fold (==1.2.0)
Requires-Dist: pytest-xdist (==1.15)
